byoa/__init__.py
byoa/__main__.py
byoa/cli/__init__.py
byoa/cli/build.py
byoa/cli/context.py
byoa/cli/delete.py
byoa/cli/deploy.py
byoa/cli/init.py
byoa/cli/manifest.py
byoa/cli/run.py
byoa/cloud_storage/__init__.py
byoa/cloud_storage/aws_s3.py
byoa/cloud_storage/azure_blob_storage.py
byoa/config/__init__.py
byoa/config/context.py
byoa/config/manifest.py
byoa/exceptions.py
byoa/importer.py
byoa/models.py
byoa/telemetry/__init__.py
byoa/telemetry/log_manager/__init__.py
byoa/telemetry/log_manager/log_manager.py
byoa/telemetry/log_manager/trace_formatter.py
byoa/telemetry/trace_manager/__init__.py
byoa/telemetry/trace_manager/trace_manager.py
byoa-0.1.0a5.dist-info/LICENSE
byoa-0.1.0a5.dist-info/METADATA
byoa-0.1.0a5.dist-info/WHEEL
byoa-0.1.0a5.dist-info/entry_points.txt
byoa-0.1.0a5.dist-info/RECORD
