Metadata-Version: 2.1
Name: byoa
Version: 0.1.0a5
Summary: 
Author: ada-geosys
Author-email: ada@geosys.com
Requires-Python: >=3.11,<4.0
Classifier: Programming Language :: Python :: 3
Classifier: Programming Language :: Python :: 3.11
Classifier: Programming Language :: Python :: 3.12
Requires-Dist: azure-storage-blob (>=12.18.3,<13.0.0)
Requires-Dist: boto3 (>=1.28.76,<2.0.0)
Requires-Dist: click (>=8.1.7,<9.0.0)
Requires-Dist: click-option-group (>=0.5.6,<0.6.0)
Requires-Dist: cookiecutter (>=2.4.0,<3.0.0)
Requires-Dist: docker (>=6.1.3,<7.0.0)
Requires-Dist: opentelemetry-sdk (>=1.21.0,<2.0.0)
Requires-Dist: pydantic (>=2.4.2,<3.0.0)
Requires-Dist: python-slugify (>=8.0.1,<9.0.0)
Requires-Dist: toml (>=0.10.2,<0.11.0)
